README.md
setup.py
bert_seq2seq/__init__.py
bert_seq2seq/basic_bert.py
bert_seq2seq/config.py
bert_seq2seq/dataset.py
bert_seq2seq/glm_tokenizer.py
bert_seq2seq/launch.py
bert_seq2seq/layers.py
bert_seq2seq/tokenizer.py
bert_seq2seq/trainer.py
bert_seq2seq/utils.py
bert_seq2seq/model/__init__.py
bert_seq2seq/model/bart_model.py
bert_seq2seq/model/bert_model.py
bert_seq2seq/model/glm_model.py
bert_seq2seq/model/gpt2_model.py
bert_seq2seq/model/nezha_model.py
bert_seq2seq/model/prompt.py
bert_seq2seq/model/roberta_model.py
bert_seq2seq/model/t5_model.py
bert_seq2seq/model/utils.py
bert_seq2seq/model/blocks/__init__.py
bert_seq2seq/model/blocks/glm_block.py
bert_seq2seq/model/layers/__init__.py
bert_seq2seq/model/layers/activations.py
bert_seq2seq/model/layers/attentions.py
bert_seq2seq/model/layers/embeddings.py
bert_seq2seq/model/layers/feedforward.py
bert_seq2seq/model/layers/layer_norm.py
bert_seq2seq/mpu/__init__.py
bert_seq2seq/mpu/cross_entropy.py
bert_seq2seq/mpu/data.py
bert_seq2seq/mpu/func_utils.py
bert_seq2seq/mpu/grads.py
bert_seq2seq/mpu/initialize.py
bert_seq2seq/mpu/mappings.py
bert_seq2seq/mpu/mp_tools.py
bert_seq2seq/mpu/random.py
bert_seq2seq/mpu/utils.py
bert_seq2seq/predictor/__init__.py
bert_seq2seq/predictor/predictor.py
bert_seq2seq/predictor/utils.py
bert_seq2seq/task/__init__.py
bert_seq2seq/task/classification/__init__.py
bert_seq2seq/task/classification/bert_cls_classifier.py
bert_seq2seq/task/embedding/__init__.py
bert_seq2seq/task/embedding/bert_embedding.py
bert_seq2seq/task/relationship_extraction/__init__.py
bert_seq2seq/task/relationship_extraction/bert_relationship_extraction.py
bert_seq2seq/task/seq2seq/GLM_seq2seq_model.py
bert_seq2seq/task/seq2seq/__init__.py
bert_seq2seq/task/seq2seq/bert_seq2seq_model.py
bert_seq2seq/task/seq2seq/gpt2_seq2seq_model.py
bert_seq2seq/task/seq2seq/t5_seq2seq_model.py
bert_seq2seq/task/sequence_labeling/__init__.py
bert_seq2seq/task/sequence_labeling/bert_sequence_labeling.py
bert_seq2seq_DDP.egg-info/PKG-INFO
bert_seq2seq_DDP.egg-info/SOURCES.txt
bert_seq2seq_DDP.egg-info/dependency_links.txt
bert_seq2seq_DDP.egg-info/top_level.txt