Metadata-Version: 1.0
Name: bert-seq2seq-DDP
Version: 0.2.0
Summary: use torch to do bert_seq2seq task
Home-page: https://github.com/920232796/bert_seq2seq_DDP
Author: xingzhaohu
Author-email: 920232796@qq.com
License: Apache License 2.0
Platform: UNKNOWN
